styles/vkr.css
vkr_build/__init__.py
vkr_build/__main__.py
vkr_build/config.py
vkr_build/console.py
vkr_build/document_builder.py
vkr_build/toc.py
vkr_build/utils.py
vkr_build-0.1.2.dist-info/LICENSE
vkr_build-0.1.2.dist-info/METADATA
vkr_build-0.1.2.dist-info/WHEEL
vkr_build-0.1.2.dist-info/entry_points.txt
vkr_build-0.1.2.dist-info/RECORD
