Metadata-Version: 2.1
Name: vkr-build
Version: 0.1.2
Summary: Автоматизированное решение вёрстки курсовых/дипломных работ.
License: MIT
Author: dx3mod
Requires-Python: >=3.12,<4.0
Classifier: License :: OSI Approved :: MIT License
Classifier: Programming Language :: Python :: 3
Classifier: Programming Language :: Python :: 3.12
Requires-Dist: beautifulsoup4 (>=4.12.3,<5.0.0)
Requires-Dist: pydantic (>=2.7.4,<3.0.0)
Requires-Dist: pypandoc (>=1.13,<2.0)
Requires-Dist: weasyprint (>=62.3,<63.0)
